LICENSE
MANIFEST.in
README.md
setup.py
RL4Grid/base_env.py
RL4Grid/observation.py
RL4Grid/rewards.py
RL4Grid/test.py
RL4Grid.egg-info/PKG-INFO
RL4Grid.egg-info/SOURCES.txt
RL4Grid.egg-info/dependency_links.txt
RL4Grid.egg-info/requires.txt
RL4Grid.egg-info/top_level.txt
RL4Grid/game/gridsim/__init__.py
RL4Grid/game/gridsim/env_wrapper.py
RL4Grid/game/gridsim/utils.py
RL4Grid/model_jm/case126.py
RL4Grid/model_jm/case14.py
RL4Grid/model_jm/case2000.py
RL4Grid/model_jm/case300.py
RL4Grid/model_jm/case39.py
RL4Grid/model_jm/case57.py
RL4Grid/model_jm/convert_tx2000_mat_py.py
RL4Grid/model_jm/plot_sg126_net.py
RL4Grid/utilize/action_space.py
RL4Grid/utilize/form_action.py
RL4Grid/utilize/legal_action.py
RL4Grid/utilize/line_cutting.py
RL4Grid/utilize/read_forecast_value.py
RL4Grid/utilize/exceptions/action_illegal_exceptions.py