Metadata-Version: 2.1
Name: RL4Grid
Version: 0.2.0.1
Summary: An RL Env for optimal dispatching
Home-page: https://github.com/liushaohuai5/RL4Grid
Author: Shaohuai Liu
Author-email: liushaohuai42@gmail.com
License: UNKNOWN
Platform: UNKNOWN
Classifier: Programming Language :: Python :: 3
Classifier: License :: OSI Approved :: MIT License
Classifier: Operating System :: OS Independent
